{
  "Major": 0,
  "Minor": 1,
  "Patch": 0,
  "PreReleaseTag": "alpha.27",
  "PreReleaseTagWithDash": "-alpha.27",
  "PreReleaseLabel": "alpha",
  "PreReleaseLabelWithDash": "-alpha",
  "PreReleaseNumber": 27,
  "WeightedPreReleaseNumber": 27,
  "BuildMetaData": null,
  "BuildMetaDataPadded": "",
  "FullBuildMetaData": "Branch.develop.Sha.5956971e78d56278a715cb77ee9cb096f7add78a",
  "MajorMinorPatch": "0.1.0",
  "SemVer": "0.1.0-alpha.27",
  "LegacySemVer": "0.1.0-alpha27",
  "LegacySemVerPadded": "0.1.0-alpha0027",
  "AssemblySemVer": "0.1.0.0",
  "AssemblySemFileVer": "0.1.0.0",
  "FullSemVer": "0.1.0-alpha.27",
  "InformationalVersion": "0.1.0-alpha.27+Branch.develop.Sha.5956971e78d56278a715cb77ee9cb096f7add78a",
  "BranchName": "develop",
  "EscapedBranchName": "develop",
  "Sha": "5956971e78d56278a715cb77ee9cb096f7add78a",
  "ShortSha": "5956971",
  "NuGetVersionV2": "0.1.0-alpha0027",
  "NuGetVersion": "0.1.0-alpha0027",
  "NuGetPreReleaseTagV2": "alpha0027",
  "NuGetPreReleaseTag": "alpha0027",
  "VersionSourceSha": "c8dd54f5a84f8e058abce2a36193c1ebed9e8cd0",
  "CommitsSinceVersionSource": 27,
  "CommitsSinceVersionSourcePadded": "0027",
  "UncommittedChanges": 29,
  "CommitDate": "2023-11-23"
}